Metadata-Version: 2.1
Name: Flask-KVSession-Invenio
Version: 0.6.4
Summary: Transparent server-side session support for flask
Home-page: https://github.com/mbr/flask-kvsession
Author: Marc Brinkmann
Author-email: git@marcbrinkmann.de
License: MIT
Platform: any
Classifier: Programming Language :: Python :: 3
Classifier: Programming Language :: Python :: 3.6
Classifier: Programming Language :: Python :: 3.7
License-File: LICENSE
Requires-Dist: Flask >=0.8
Requires-Dist: itsdangerous >=0.20
Requires-Dist: simplekv >=0.9.2
Requires-Dist: six
Requires-Dist: werkzeug
